programgarden/__init__.py
programgarden/buysell_executor.py
programgarden/client.py
programgarden/condition_executor.py
programgarden/performance_monitor.py
programgarden/pg_listener.py
programgarden/plugin_resolver.py
programgarden/real_order_executor.py
programgarden/symbols_provider.py
programgarden/system_executor.py
programgarden/system_keys.py
programgarden-0.1.28.dist-info/METADATA
programgarden-0.1.28.dist-info/WHEEL
programgarden-0.1.28.dist-info/RECORD
