Metadata-Version: 2.3
Name: programgarden
Version: 0.1.28
Summary: 자동화매매 오픈소스의 실행, 로그, 환경 등의 핵심이되는 오픈소스
Author: 프로그램동산
Author-email: coding@programgarden.com
Requires-Python: >=3.10
Classifier: Programming Language :: Python :: 3
Classifier: Programming Language :: Python :: 3.10
Classifier: Programming Language :: Python :: 3.11
Classifier: Programming Language :: Python :: 3.12
Classifier: Programming Language :: Python :: 3.13
Requires-Dist: croniter (>=6.0.0,<7.0.0)
Requires-Dist: jsoneditor (>=1.6.0,<2.0.0)
Requires-Dist: programgarden-community (==0.1.15)
Requires-Dist: programgarden-core (>=0.1.12,<0.2.0)
Requires-Dist: programgarden-finance (>=0.1.13,<0.2.0)
Requires-Dist: psutil (>=7.1.3,<8.0.0)
Requires-Dist: pydantic (>=2.11.7,<3.0.0)
Requires-Dist: python-dotenv (>=1.1.1,<2.0.0)
Requires-Dist: tzdata (>=2025.2,<2026.0)
